{
  "dish": [
    {
      "ID": 1,
      "name": "Борщ",
      "cost": 50
    },
    {
      "ID": 2,
      "name": "Шницель з картоплею",
      "cost": 120
    },
    {
      "ID": 3,
      "name": "Лазанья",
      "cost": 90
    },
    {
      "ID": 4,
      "name": "Цезар з куркою",
      "cost": 80
    },
    {
      "ID": 5,
      "name": "Піца Маргарита",
      "cost": 70
    },
    {
      "ID": 6,
      "name": "Салат Грецький",
      "cost": 60
    }
  ],
  "drink": [
    {
      "ID": 1,
      "name": "Кава",
      "cost": 30
    },
    {
      "ID": 2,
      "name": "Чай",
      "cost": 20
    },
    {
      "ID": 3,
      "name": "Сік апельсиновий",
      "cost": 25
    },
    {
      "ID": 4,
      "name": "Лимонад",
      "cost": 35
    },
    {
      "ID": 5,
      "name": "Коктейль Мохіто",
      "cost": 50
    },
    {
      "ID": 6,
      "name": "Вино червоне",
      "cost": 70
    }
  ]
}
